{"items":[{"name":"독산주공14단지","district":"독산동","area_m2":38.64,"floor":5,"price_10k":37000,"deal_date":"2026-03-31","build_year":1990,"deal_type":"중개거래"},{"name":"우방","district":"시흥동","area_m2":59.91,"floor":1,"price_10k":39000,"deal_date":"2026-03-04","build_year":2002,"deal_type":"중개거래"},{"name":"성지","district":"시흥동","area_m2":67.27,"floor":1,"price_10k":53000,"deal_date":"2026-03-20","build_year":1986,"deal_type":"중개거래"},{"name":"무지개","district":"시흥동","area_m2":53.75,"floor":5,"price_10k":46000,"deal_date":"2026-03-24","build_year":1980,"deal_type":"중개거래"},{"name":"e편한세상독산더타워","district":"독산동","area_m2":59.6222,"floor":21,"price_10k":81000,"deal_date":"2026-03-30","build_year":2019,"deal_type":"중개거래"},{"name":"무지개","district":"시흥동","area_m2":53.88,"floor":1,"price_10k":44800,"deal_date":"2026-03-26","build_year":1980,"deal_type":"중개거래"},{"name":"e편한세상독산더타워","district":"독산동","area_m2":84.9256,"floor":13,"price_10k":97900,"deal_date":"2026-03-30","build_year":2019,"deal_type":"중개거래"},{"name":"무지개","district":"시흥동","area_m2":53.79,"floor":8,"price_10k":45500,"deal_date":"2026-03-14","build_year":1980,"deal_type":"중개거래"},{"name":"무지개","district":"시흥동","area_m2":53.79,"floor":9,"price_10k":45500,"deal_date":"2026-03-26","build_year":1980,"deal_type":"중개거래"},{"name":"e편한세상독산더타워","district":"독산동","area_m2":74.9482,"floor":31,"price_10k":88000,"deal_date":"2026-03-21","build_year":2019,"deal_type":"중개거래"},{"name":"남서울건영아파트","district":"시흥동","area_m2":77.02,"floor":13,"price_10k":53500,"deal_date":"2026-03-21","build_year":1982,"deal_type":"중개거래"},{"name":"현대(209)","district":"시흥동","area_m2":82.53,"floor":8,"price_10k":44000,"deal_date":"2026-03-25","build_year":1996,"deal_type":"중개거래"},{"name":"무지개","district":"시흥동","area_m2":53.75,"floor":8,"price_10k":46000,"deal_date":"2026-03-19","build_year":1980,"deal_type":"중개거래"},{"name":"백운한비치","district":"시흥동","area_m2":76.0537,"floor":5,"price_10k":53100,"deal_date":"2026-03-23","build_year":2003,"deal_type":"중개거래"},{"name":"청광플러스원","district":"독산동","area_m2":84.962,"floor":5,"price_10k":65000,"deal_date":"2026-03-31","build_year":2003,"deal_type":"중개거래"},{"name":"남서울힐스테이트","district":"시흥동","area_m2":115.801,"floor":14,"price_10k":98000,"deal_date":"2026-03-27","build_year":2014,"deal_type":"직거래"},{"name":"무지개","district":"시흥동","area_m2":53.75,"floor":2,"price_10k":45600,"deal_date":"2026-03-15","build_year":1980,"deal_type":"중개거래"},{"name":"두산","district":"가산동","area_m2":84.9,"floor":8,"price_10k":73000,"deal_date":"2026-03-29","build_year":1998,"deal_type":"중개거래"},{"name":"두산","district":"가산동","area_m2":84.9,"floor":12,"price_10k":73000,"deal_date":"2026-03-30","build_year":1998,"deal_type":"중개거래"},{"name":"진도3차아파트","district":"독산동","area_m2":59.34,"floor":4,"price_10k":50000,"deal_date":"2026-03-30","build_year":1999,"deal_type":"중개거래"},{"name":"해찬행복드림","district":"가산동","area_m2":84.45,"floor":10,"price_10k":57500,"deal_date":"2026-03-07","build_year":2008,"deal_type":"중개거래"},{"name":"금천롯데캐슬골드파크3차","district":"독산동","area_m2":84.4855,"floor":24,"price_10k":120000,"deal_date":"2026-03-31","build_year":2018,"deal_type":"중개거래"},{"name":"금천현대","district":"독산동","area_m2":84.83,"floor":22,"price_10k":69200,"deal_date":"2026-03-30","build_year":2002,"deal_type":"중개거래"},{"name":"금천현대","district":"독산동","area_m2":59.82,"floor":1,"price_10k":53000,"deal_date":"2026-03-28","build_year":2002,"deal_type":"중개거래"},{"name":"금광","district":"시흥동","area_m2":83.2925,"floor":4,"price_10k":40000,"deal_date":"2026-03-12","build_year":2004,"deal_type":"직거래"},{"name":"신도브래뉴","district":"독산동","area_m2":73.2,"floor":13,"price_10k":70100,"deal_date":"2026-03-26","build_year":2002,"deal_type":"중개거래"},{"name":"삼익","district":"가산동","area_m2":84.69,"floor":1,"price_10k":53500,"deal_date":"2026-03-30","build_year":1998,"deal_type":"중개거래"},{"name":"한신아파트","district":"독산동","area_m2":129.66,"floor":1,"price_10k":81000,"deal_date":"2026-03-30","build_year":1991,"deal_type":"중개거래"},{"name":"한빛","district":"시흥동","area_m2":84.96,"floor":3,"price_10k":41000,"deal_date":"2026-03-28","build_year":2001,"deal_type":"중개거래"},{"name":"금천현대","district":"독산동","area_m2":59.82,"floor":4,"price_10k":61000,"deal_date":"2026-03-28","build_year":2002,"deal_type":"중개거래"},{"name":"독산주공14단지","district":"독산동","area_m2":38.64,"floor":9,"price_10k":34700,"deal_date":"2026-03-28","build_year":1990,"deal_type":"중개거래"},{"name":"남서울건영2","district":"시흥동","area_m2":61.14,"floor":7,"price_10k":43000,"deal_date":"2026-03-23","build_year":1989,"deal_type":"중개거래"},{"name":"남서울힐스테이트","district":"시흥동","area_m2":59.817,"floor":11,"price_10k":83100,"deal_date":"2026-03-27","build_year":2014,"deal_type":"중개거래"},{"name":"목화102","district":"독산동","area_m2":59.96,"floor":6,"price_10k":40800,"deal_date":"2026-03-28","build_year":1997,"deal_type":"중개거래"},{"name":"관악산벽산타운5","district":"시흥동","area_m2":84.97,"floor":7,"price_10k":56000,"deal_date":"2026-03-28","build_year":2004,"deal_type":"중개거래"},{"name":"관악산벽산타운5","district":"시흥동","area_m2":84.97,"floor":5,"price_10k":51600,"deal_date":"2026-03-28","build_year":2004,"deal_type":"중개거래"},{"name":"금천롯데캐슬골드파크1차","district":"독산동","area_m2":84.4623,"floor":7,"price_10k":116500,"deal_date":"2026-03-21","build_year":2016,"deal_type":"중개거래"},{"name":"금천롯데캐슬골드파크3차","district":"독산동","area_m2":59.968,"floor":12,"price_10k":98000,"deal_date":"2026-03-28","build_year":2018,"deal_type":"중개거래"},{"name":"남서울건영2","district":"시흥동","area_m2":41.34,"floor":12,"price_10k":31700,"deal_date":"2026-03-25","build_year":1989,"deal_type":"중개거래"},{"name":"금천롯데캐슬골드파크3차","district":"독산동","area_m2":59.9662,"floor":45,"price_10k":104000,"deal_date":"2026-03-27","build_year":2018,"deal_type":"중개거래"},{"name":"금천롯데캐슬골드파크2차201동202동","district":"독산동","area_m2":59.27,"floor":17,"price_10k":89000,"deal_date":"2026-03-27","build_year":2017,"deal_type":"중개거래"},{"name":"럭키남서울아파트","district":"시흥동","area_m2":49.79,"floor":10,"price_10k":51000,"deal_date":"2026-03-20","build_year":1981,"deal_type":"중개거래"},{"name":"가산지웰에스테이트2차","district":"가산동","area_m2":14.94,"floor":7,"price_10k":10000,"deal_date":"2026-03-18","build_year":2018,"deal_type":"중개거래"},{"name":"현대(209)","district":"시흥동","area_m2":82.53,"floor":5,"price_10k":44500,"deal_date":"2026-03-26","build_year":1996,"deal_type":"중개거래"},{"name":"관악산벽산타운5","district":"시흥동","area_m2":84.97,"floor":4,"price_10k":52000,"deal_date":"2026-03-25","build_year":2004,"deal_type":"직거래"},{"name":"우방","district":"시흥동","area_m2":114.89,"floor":8,"price_10k":69500,"deal_date":"2026-03-25","build_year":2002,"deal_type":"중개거래"},{"name":"관악산벽산타운5","district":"시흥동","area_m2":84.97,"floor":8,"price_10k":55000,"deal_date":"2026-03-25","build_year":2004,"deal_type":"직거래"},{"name":"금천롯데캐슬골드파크3차","district":"독산동","area_m2":59.968,"floor":24,"price_10k":95000,"deal_date":"2026-03-25","build_year":2018,"deal_type":"중개거래"},{"name":"독산주공14단지","district":"독산동","area_m2":59.22,"floor":11,"price_10k":59500,"deal_date":"2026-03-17","build_year":1990,"deal_type":"중개거래"},{"name":"남서울힐스테이트","district":"시흥동","area_m2":59.973,"floor":11,"price_10k":82500,"deal_date":"2026-03-19","build_year":2014,"deal_type":"중개거래"},{"name":"두산","district":"가산동","area_m2":59.84,"floor":14,"price_10k":67000,"deal_date":"2026-03-25","build_year":1998,"deal_type":"중개거래"},{"name":"독산주공14단지","district":"독산동","area_m2":38.64,"floor":4,"price_10k":35800,"deal_date":"2026-03-24","build_year":1990,"deal_type":"중개거래"},{"name":"관악산벽산타운5","district":"시흥동","area_m2":84.97,"floor":11,"price_10k":54000,"deal_date":"2026-03-24","build_year":2004,"deal_type":"중개거래"},{"name":"백운한비치","district":"시흥동","area_m2":73.9154,"floor":3,"price_10k":55000,"deal_date":"2026-03-23","build_year":2003,"deal_type":"중개거래"},{"name":"무지개","district":"시흥동","area_m2":53.75,"floor":7,"price_10k":45500,"deal_date":"2026-03-16","build_year":1980,"deal_type":"중개거래"},{"name":"금천롯데캐슬골드파크2차201동202동","district":"독산동","area_m2":59.98,"floor":27,"price_10k":93000,"deal_date":"2026-03-20","build_year":2017,"deal_type":"중개거래"},{"name":"진도1차","district":"독산동","area_m2":84.84,"floor":7,"price_10k":54000,"deal_date":"2026-03-20","build_year":1996,"deal_type":"중개거래"},{"name":"우방","district":"시흥동","area_m2":114.89,"floor":21,"price_10k":63500,"deal_date":"2026-03-20","build_year":2002,"deal_type":"중개거래"},{"name":"무지개","district":"시흥동","area_m2":84.96,"floor":9,"price_10k":73300,"deal_date":"2026-03-23","build_year":1980,"deal_type":"중개거래"},{"name":"한신아파트","district":"독산동","area_m2":89.46,"floor":21,"price_10k":64000,"deal_date":"2026-03-22","build_year":1991,"deal_type":"중개거래"},{"name":"럭키남서울아파트","district":"시흥동","area_m2":41.22,"floor":7,"price_10k":39000,"deal_date":"2026-03-05","build_year":1981,"deal_type":"중개거래"},{"name":"서초파레스","district":"독산동","area_m2":84.11,"floor":6,"price_10k":60000,"deal_date":"2026-03-20","build_year":2005,"deal_type":"중개거래"},{"name":"중앙아파트","district":"독산동","area_m2":35.61,"floor":5,"price_10k":24500,"deal_date":"2026-03-07","build_year":1989,"deal_type":"중개거래"},{"name":"남서울힐스테이트","district":"시흥동","area_m2":84.697,"floor":16,"price_10k":97000,"deal_date":"2026-03-19","build_year":2014,"deal_type":"중개거래"},{"name":"남서울건영2","district":"시흥동","area_m2":61.15,"floor":10,"price_10k":42000,"deal_date":"2026-03-21","build_year":1989,"deal_type":"중개거래"},{"name":"우방","district":"시흥동","area_m2":59.91,"floor":12,"price_10k":47700,"deal_date":"2026-03-22","build_year":2002,"deal_type":"중개거래"},{"name":"관악산벽산타운5","district":"시흥동","area_m2":84.97,"floor":16,"price_10k":53500,"deal_date":"2026-03-21","build_year":2004,"deal_type":"중개거래"},{"name":"금천현대","district":"독산동","area_m2":59.82,"floor":9,"price_10k":60000,"deal_date":"2026-03-20","build_year":2002,"deal_type":"중개거래"},{"name":"남서울힐스테이트","district":"시흥동","area_m2":84.786,"floor":25,"price_10k":94500,"deal_date":"2026-03-21","build_year":2014,"deal_type":"중개거래"},{"name":"관악산벽산타운5","district":"시흥동","area_m2":84.97,"floor":8,"price_10k":53300,"deal_date":"2026-03-21","build_year":2004,"deal_type":"중개거래"},{"name":"남서울힐스테이트","district":"시흥동","area_m2":84.786,"floor":3,"price_10k":90500,"deal_date":"2026-03-20","build_year":2014,"deal_type":"중개거래"},{"name":"금천롯데캐슬골드파크3차","district":"독산동","area_m2":59.9672,"floor":22,"price_10k":103800,"deal_date":"2026-03-19","build_year":2018,"deal_type":"중개거래"},{"name":"벽산","district":"시흥동","area_m2":84.99,"floor":3,"price_10k":48000,"deal_date":"2026-03-12","build_year":2000,"deal_type":"중개거래"},{"name":"남서울힐스테이트","district":"시흥동","area_m2":84.677,"floor":19,"price_10k":88500,"deal_date":"2026-03-20","build_year":2014,"deal_type":"중개거래"},{"name":"남서울건영아파트","district":"시흥동","area_m2":88.83,"floor":4,"price_10k":68500,"deal_date":"2026-03-06","build_year":1982,"deal_type":"중개거래"},{"name":"시흥동월드메르디앙","district":"시흥동","area_m2":59.88,"floor":5,"price_10k":46800,"deal_date":"2026-03-19","build_year":2006,"deal_type":"중개거래"},{"name":"금천롯데캐슬골드파크1차","district":"독산동","area_m2":84.4623,"floor":35,"price_10k":117000,"deal_date":"2026-03-19","build_year":2016,"deal_type":"중개거래"},{"name":"독산동중앙하이츠빌","district":"독산동","area_m2":84.8768,"floor":18,"price_10k":86200,"deal_date":"2026-03-16","build_year":2004,"deal_type":"중개거래"},{"name":"독산주공14단지","district":"독산동","area_m2":44.94,"floor":9,"price_10k":40000,"deal_date":"2026-03-18","build_year":1990,"deal_type":"중개거래"},{"name":"남서울힐스테이트","district":"시흥동","area_m2":84.786,"floor":25,"price_10k":89000,"deal_date":"2026-03-18","build_year":2014,"deal_type":"중개거래"},{"name":"독산주공14단지","district":"독산동","area_m2":44.89,"floor":9,"price_10k":42500,"deal_date":"2026-03-06","build_year":1990,"deal_type":"중개거래"},{"name":"SM엘루이","district":"시흥동","area_m2":71.09,"floor":2,"price_10k":51000,"deal_date":"2026-03-14","build_year":2012,"deal_type":"중개거래"},{"name":"태영아파트","district":"독산동","area_m2":56.78,"floor":17,"price_10k":43000,"deal_date":"2026-03-14","build_year":2001,"deal_type":"중개거래"},{"name":"독산주공14단지","district":"독산동","area_m2":44.89,"floor":5,"price_10k":41500,"deal_date":"2026-03-13","build_year":1990,"deal_type":"중개거래"},{"name":"우방","district":"시흥동","area_m2":59.91,"floor":14,"price_10k":49400,"deal_date":"2026-03-16","build_year":2002,"deal_type":"중개거래"},{"name":"두산","district":"가산동","area_m2":84.9,"floor":17,"price_10k":74500,"deal_date":"2026-03-10","build_year":1998,"deal_type":"중개거래"},{"name":"남서울건영2","district":"시흥동","area_m2":41.34,"floor":14,"price_10k":32300,"deal_date":"2026-03-14","build_year":1989,"deal_type":"중개거래"},{"name":"금천롯데캐슬골드파크3차","district":"독산동","area_m2":59.9662,"floor":43,"price_10k":104500,"deal_date":"2026-03-14","build_year":2018,"deal_type":"중개거래"},{"name":"관악산벽산타운5","district":"시흥동","area_m2":59.34,"floor":11,"price_10k":44900,"deal_date":"2026-03-14","build_year":2004,"deal_type":"중개거래"},{"name":"남서울건영2","district":"시흥동","area_m2":61.23,"floor":11,"price_10k":40000,"deal_date":"2026-03-14","build_year":1989,"deal_type":"중개거래"},{"name":"관악산벽산타운5","district":"시흥동","area_m2":84.97,"floor":10,"price_10k":58300,"deal_date":"2026-03-14","build_year":2004,"deal_type":"중개거래"},{"name":"삼일","district":"시흥동","area_m2":59.91,"floor":2,"price_10k":33000,"deal_date":"2026-03-14","build_year":1997,"deal_type":"중개거래"},{"name":"시흥베르빌","district":"시흥동","area_m2":81.16,"floor":15,"price_10k":75000,"deal_date":"2026-03-14","build_year":2004,"deal_type":"중개거래"},{"name":"한신아파트","district":"독산동","area_m2":129.66,"floor":2,"price_10k":77500,"deal_date":"2026-03-03","build_year":1991,"deal_type":"중개거래"},{"name":"두산","district":"가산동","area_m2":84.9,"floor":3,"price_10k":68500,"deal_date":"2026-03-12","build_year":1998,"deal_type":"중개거래"},{"name":"벽산","district":"시흥동","area_m2":84.99,"floor":10,"price_10k":52000,"deal_date":"2026-03-08","build_year":2000,"deal_type":"중개거래"},{"name":"관악산벽산타운5","district":"시흥동","area_m2":84.97,"floor":10,"price_10k":54000,"deal_date":"2026-03-06","build_year":2004,"deal_type":"중개거래"},{"name":"남서울힐스테이트","district":"시흥동","area_m2":84.697,"floor":8,"price_10k":94000,"deal_date":"2026-03-09","build_year":2014,"deal_type":"중개거래"},{"name":"남서울힐스테이트","district":"시흥동","area_m2":59.973,"floor":9,"price_10k":83200,"deal_date":"2026-03-09","build_year":2014,"deal_type":"중개거래"},{"name":"신도브래뉴","district":"독산동","area_m2":55.55,"floor":5,"price_10k":58000,"deal_date":"2026-03-09","build_year":2002,"deal_type":"중개거래"},{"name":"금천롯데캐슬골드파크3차","district":"독산동","area_m2":84.408,"floor":10,"price_10k":119500,"deal_date":"2026-03-09","build_year":2018,"deal_type":"중개거래"},{"name":"벽산","district":"시흥동","area_m2":59.94,"floor":10,"price_10k":36800,"deal_date":"2026-03-09","build_year":2000,"deal_type":"중개거래"},{"name":"남서울힐스테이트","district":"시흥동","area_m2":59.817,"floor":1,"price_10k":78000,"deal_date":"2026-03-07","build_year":2014,"deal_type":"중개거래"},{"name":"남서울힐스테이트","district":"시흥동","area_m2":150.72,"floor":19,"price_10k":140000,"deal_date":"2026-03-05","build_year":2014,"deal_type":"중개거래"},{"name":"독산주공14단지","district":"독산동","area_m2":44.89,"floor":1,"price_10k":38500,"deal_date":"2026-03-06","build_year":1990,"deal_type":"중개거래"},{"name":"한신아파트","district":"독산동","area_m2":89.46,"floor":15,"price_10k":64200,"deal_date":"2026-03-04","build_year":1991,"deal_type":"중개거래"},{"name":"벽산","district":"시흥동","area_m2":59.94,"floor":19,"price_10k":41300,"deal_date":"2026-03-05","build_year":2000,"deal_type":"중개거래"},{"name":"독산주공14단지","district":"독산동","area_m2":44.89,"floor":3,"price_10k":40000,"deal_date":"2026-03-03","build_year":1990,"deal_type":"중개거래"},{"name":"남서울힐스테이트","district":"시흥동","area_m2":115.801,"floor":9,"price_10k":104500,"deal_date":"2026-03-04","build_year":2014,"deal_type":"중개거래"},{"name":"독산주공14단지","district":"독산동","area_m2":38.64,"floor":5,"price_10k":36000,"deal_date":"2026-03-03","build_year":1990,"deal_type":"중개거래"},{"name":"두산","district":"가산동","area_m2":101.67,"floor":17,"price_10k":81000,"deal_date":"2026-03-03","build_year":1998,"deal_type":"중개거래"},{"name":"삼익","district":"시흥동","area_m2":59.9,"floor":2,"price_10k":43000,"deal_date":"2026-03-01","build_year":1999,"deal_type":"중개거래"},{"name":"삼익","district":"시흥동","area_m2":59.86,"floor":9,"price_10k":48000,"deal_date":"2026-03-01","build_year":1999,"deal_type":"중개거래"},{"name":"삼익","district":"독산동","area_m2":59.96,"floor":11,"price_10k":45000,"deal_date":"2026-03-02","build_year":1998,"deal_type":"중개거래"}],"summary":{"median_price_10k":54000,"min_price_10k":10000,"max_price_10k":140000,"sample_count":114},"total_count":115,"filtered_count":114,"query":{"asset_type":"apartment","deal_type":"trade","lawd_cd":"11545","deal_ymd":"202603"},"proxy":{"name":"k-skill-proxy","cache":{"hit":false,"ttl_ms":300000},"requested_at":"2026-05-06T04:06:24.004Z"}}