{"items":[{"name":"연희파크푸르지오","district":"연희동","area_m2":84.4317,"floor":11,"price_10k":96500,"deal_date":"2023-05-12","build_year":2018,"deal_type":"중개거래"},{"name":"돈의문센트레빌","district":"냉천동","area_m2":84.99,"floor":3,"price_10k":99250,"deal_date":"2023-05-15","build_year":2011,"deal_type":"중개거래"},{"name":"DMC현대아파트","district":"북가좌동","area_m2":83.7,"floor":3,"price_10k":66000,"deal_date":"2023-05-27","build_year":2000,"deal_type":"중개거래"},{"name":"신촌럭키","district":"대현동","area_m2":59.7,"floor":5,"price_10k":76000,"deal_date":"2023-05-28","build_year":1999,"deal_type":"중개거래"},{"name":"DMC래미안e편한세상","district":"북가좌동","area_m2":84.94,"floor":25,"price_10k":109500,"deal_date":"2023-05-27","build_year":2012,"deal_type":"중개거래"},{"name":"연희파크푸르지오","district":"연희동","area_m2":84.4317,"floor":1,"price_10k":90000,"deal_date":"2023-05-24","build_year":2018,"deal_type":"중개거래"},{"name":"동일2차","district":"홍제동","area_m2":81.62,"floor":4,"price_10k":52500,"deal_date":"2023-05-29","build_year":2002,"deal_type":"중개거래"},{"name":"DMC래미안e편한세상","district":"북가좌동","area_m2":59.97,"floor":16,"price_10k":90000,"deal_date":"2023-05-30","build_year":2012,"deal_type":"중개거래"},{"name":"DMC파크뷰자이3단지","district":"남가좌동","area_m2":59.981,"floor":13,"price_10k":90000,"deal_date":"2023-05-27","build_year":2015,"deal_type":"중개거래"},{"name":"청구1차","district":"홍제동","area_m2":84.78,"floor":15,"price_10k":85000,"deal_date":"2023-05-27","build_year":1994,"deal_type":"중개거래"},{"name":"남가좌동현대","district":"남가좌동","area_m2":59.4,"floor":9,"price_10k":65000,"deal_date":"2023-05-31","build_year":1999,"deal_type":"중개거래"},{"name":"홍은동풍림아이원","district":"홍은동","area_m2":116.101,"floor":15,"price_10k":77000,"deal_date":"2023-05-28","build_year":2002,"deal_type":"중개거래"},{"name":"DMC서부인터빌","district":"북가좌동","area_m2":84.66,"floor":13,"price_10k":84000,"deal_date":"2023-05-22","build_year":2008,"deal_type":"중개거래"},{"name":"DMC파크뷰자이1단지","district":"남가좌동","area_m2":120.492,"floor":18,"price_10k":151500,"deal_date":"2023-05-30","build_year":2015,"deal_type":"중개거래"},{"name":"연희파크푸르지오","district":"연희동","area_m2":84.4317,"floor":9,"price_10k":98000,"deal_date":"2023-05-29","build_year":2018,"deal_type":"중개거래"},{"name":"DMC파크뷰자이1단지","district":"남가좌동","area_m2":152.146,"floor":26,"price_10k":191000,"deal_date":"2023-05-30","build_year":2015,"deal_type":"중개거래"},{"name":"DMC래미안클라시스","district":"남가좌동","area_m2":59.97,"floor":3,"price_10k":67500,"deal_date":"2023-05-30","build_year":2000,"deal_type":"중개거래"},{"name":"독립문극동(200-0)","district":"현저동","area_m2":59.58,"floor":22,"price_10k":88000,"deal_date":"2023-05-31","build_year":1998,"deal_type":"중개거래"},{"name":"DMC래미안e편한세상","district":"북가좌동","area_m2":120.93,"floor":16,"price_10k":142000,"deal_date":"2023-05-27","build_year":2012,"deal_type":"중개거래"},{"name":"래미안남가좌2차","district":"남가좌동","area_m2":84.806,"floor":10,"price_10k":97000,"deal_date":"2023-05-31","build_year":2005,"deal_type":"중개거래"},{"name":"DMC래미안클라시스","district":"남가좌동","area_m2":59.59,"floor":11,"price_10k":68500,"deal_date":"2023-05-20","build_year":2000,"deal_type":"중개거래"},{"name":"DMC센트럴아이파크","district":"남가좌동","area_m2":84.97,"floor":4,"price_10k":104500,"deal_date":"2023-05-23","build_year":2018,"deal_type":"중개거래"},{"name":"유원","district":"홍은동","area_m2":64.26,"floor":13,"price_10k":44000,"deal_date":"2023-05-27","build_year":1987,"deal_type":"중개거래"},{"name":"DMC래미안클라시스","district":"남가좌동","area_m2":59.93,"floor":2,"price_10k":68000,"deal_date":"2023-05-25","build_year":2000,"deal_type":"중개거래"},{"name":"DMC에코자이","district":"남가좌동","area_m2":59.79,"floor":10,"price_10k":93500,"deal_date":"2023-05-29","build_year":2019,"deal_type":"중개거래"},{"name":"독립문극동(200-0)","district":"현저동","area_m2":59.58,"floor":6,"price_10k":79000,"deal_date":"2023-05-19","build_year":1998,"deal_type":"중개거래"},{"name":"DMC래미안e편한세상","district":"북가좌동","area_m2":59.97,"floor":5,"price_10k":87700,"deal_date":"2023-05-26","build_year":2012,"deal_type":"중개거래"},{"name":"e편한세상신촌1단지","district":"북아현동","area_m2":84.98,"floor":15,"price_10k":139000,"deal_date":"2023-05-23","build_year":2018,"deal_type":"중개거래"},{"name":"홍제원현대(459-0)","district":"홍제동","area_m2":59.93,"floor":9,"price_10k":63000,"deal_date":"2023-05-30","build_year":2000,"deal_type":"중개거래"},{"name":"드리밍아파트","district":"연희동","area_m2":79.26,"floor":9,"price_10k":48000,"deal_date":"2023-05-22","build_year":2006,"deal_type":"중개거래"},{"name":"e편한세상신촌1단지","district":"북아현동","area_m2":84.98,"floor":3,"price_10k":135000,"deal_date":"2023-05-31","build_year":2018,"deal_type":"중개거래"},{"name":"e편한세상신촌1단지","district":"북아현동","area_m2":84.93,"floor":11,"price_10k":138000,"deal_date":"2023-05-26","build_year":2018,"deal_type":"중개거래"},{"name":"인왕산현대","district":"홍제동","area_m2":84.9,"floor":15,"price_10k":79000,"deal_date":"2023-05-22","build_year":2000,"deal_type":"중개거래"},{"name":"래미안루센티아","district":"남가좌동","area_m2":114.93,"floor":8,"price_10k":167500,"deal_date":"2023-05-30","build_year":2020,"deal_type":"중개거래"},{"name":"독립문파크빌","district":"현저동","area_m2":59.4,"floor":8,"price_10k":58800,"deal_date":"2023-05-27","build_year":2000,"deal_type":"중개거래"},{"name":"e편한세상신촌1단지","district":"북아현동","area_m2":84.98,"floor":16,"price_10k":140300,"deal_date":"2023-05-15","build_year":2018,"deal_type":"중개거래"},{"name":"DMC파크뷰자이2단지","district":"남가좌동","area_m2":84.968,"floor":6,"price_10k":112000,"deal_date":"2023-05-19","build_year":2015,"deal_type":"중개거래"},{"name":"DMC래미안e편한세상","district":"북가좌동","area_m2":59.97,"floor":9,"price_10k":90000,"deal_date":"2023-05-18","build_year":2012,"deal_type":"중개거래"},{"name":"천연뜨란채","district":"천연동","area_m2":55.85,"floor":12,"price_10k":71000,"deal_date":"2023-05-29","build_year":2006,"deal_type":"중개거래"},{"name":"천연뜨란채","district":"천연동","area_m2":55.85,"floor":11,"price_10k":71000,"deal_date":"2023-05-20","build_year":2006,"deal_type":"중개거래"},{"name":"천연뜨란채","district":"천연동","area_m2":59.47,"floor":1,"price_10k":74000,"deal_date":"2023-05-24","build_year":2006,"deal_type":"중개거래"},{"name":"DMC파크뷰자이2단지","district":"남가좌동","area_m2":84.968,"floor":19,"price_10k":119500,"deal_date":"2023-05-21","build_year":2015,"deal_type":"중개거래"},{"name":"DMC파크뷰자이2단지","district":"남가좌동","area_m2":84.968,"floor":3,"price_10k":109000,"deal_date":"2023-05-22","build_year":2015,"deal_type":"중개거래"},{"name":"e편한세상신촌2단지","district":"북아현동","area_m2":84.98,"floor":11,"price_10k":142000,"deal_date":"2023-05-27","build_year":2018,"deal_type":"중개거래"},{"name":"신촌럭키","district":"대현동","area_m2":59.7,"floor":12,"price_10k":76000,"deal_date":"2023-05-23","build_year":1999,"deal_type":"중개거래"},{"name":"DMC한양","district":"북가좌동","area_m2":84.33,"floor":2,"price_10k":75000,"deal_date":"2023-05-22","build_year":1987,"deal_type":"중개거래"},{"name":"성원","district":"연희동","area_m2":84.95,"floor":17,"price_10k":84000,"deal_date":"2023-05-26","build_year":2001,"deal_type":"중개거래"},{"name":"북가좌삼호","district":"북가좌동","area_m2":84.57,"floor":2,"price_10k":75000,"deal_date":"2023-05-10","build_year":1996,"deal_type":"중개거래"},{"name":"두산","district":"북아현동","area_m2":59.96,"floor":12,"price_10k":75500,"deal_date":"2023-05-20","build_year":1999,"deal_type":"중개거래"},{"name":"두산","district":"북아현동","area_m2":59.96,"floor":10,"price_10k":77500,"deal_date":"2023-05-16","build_year":1999,"deal_type":"중개거래"},{"name":"홍제한양","district":"홍제동","area_m2":60.06,"floor":14,"price_10k":64500,"deal_date":"2023-05-19","build_year":1993,"deal_type":"중개거래"},{"name":"독립문극동(200-0)","district":"현저동","area_m2":84.87,"floor":16,"price_10k":100000,"deal_date":"2023-05-12","build_year":1998,"deal_type":"중개거래"},{"name":"청구1차","district":"홍제동","area_m2":84.78,"floor":10,"price_10k":81500,"deal_date":"2023-05-13","build_year":1994,"deal_type":"중개거래"},{"name":"두산","district":"홍은동","area_m2":59.61,"floor":14,"price_10k":62000,"deal_date":"2023-05-14","build_year":1997,"deal_type":"중개거래"},{"name":"북한산더샵","district":"홍은동","area_m2":84.832,"floor":19,"price_10k":113000,"deal_date":"2023-05-31","build_year":2017,"deal_type":"중개거래"},{"name":"경남(2차)","district":"북아현동","area_m2":172.9,"floor":7,"price_10k":116100,"deal_date":"2023-05-16","build_year":1999,"deal_type":"중개거래"},{"name":"독립문극동(200-0)","district":"현저동","area_m2":84.87,"floor":1,"price_10k":86000,"deal_date":"2023-05-09","build_year":1998,"deal_type":"중개거래"},{"name":"DMC센트레빌","district":"남가좌동","area_m2":84.87,"floor":6,"price_10k":99500,"deal_date":"2023-05-27","build_year":2009,"deal_type":"중개거래"},{"name":"두산","district":"북아현동","area_m2":59.96,"floor":2,"price_10k":71000,"deal_date":"2023-05-18","build_year":1999,"deal_type":"중개거래"},{"name":"북가좌삼호","district":"북가좌동","area_m2":75.75,"floor":2,"price_10k":62000,"deal_date":"2023-05-19","build_year":1996,"deal_type":"중개거래"},{"name":"북한산더샵","district":"홍은동","area_m2":84.85,"floor":17,"price_10k":101500,"deal_date":"2023-05-10","build_year":2017,"deal_type":"중개거래"},{"name":"DMC파크뷰자이2단지","district":"남가좌동","area_m2":84.968,"floor":2,"price_10k":108500,"deal_date":"2023-05-27","build_year":2015,"deal_type":"중개거래"},{"name":"북한산두산위브","district":"홍은동","area_m2":84.78,"floor":3,"price_10k":78200,"deal_date":"2023-05-27","build_year":2020,"deal_type":"중개거래"},{"name":"DMC센트럴아이파크","district":"남가좌동","area_m2":59.91,"floor":4,"price_10k":87000,"deal_date":"2023-05-13","build_year":2018,"deal_type":"중개거래"},{"name":"독립문삼호","district":"영천동","area_m2":75.66,"floor":3,"price_10k":80000,"deal_date":"2023-05-11","build_year":1995,"deal_type":"중개거래"},{"name":"DMC센트럴아이파크","district":"남가좌동","area_m2":59.91,"floor":12,"price_10k":87000,"deal_date":"2023-05-26","build_year":2018,"deal_type":"중개거래"},{"name":"연희자이엘라","district":"연희동","area_m2":13.642,"floor":7,"price_10k":15000,"deal_date":"2023-05-27","build_year":2014,"deal_type":"중개거래"},{"name":"북한산더샵","district":"홍은동","area_m2":59.865,"floor":15,"price_10k":83800,"deal_date":"2023-05-27","build_year":2017,"deal_type":"중개거래"},{"name":"DMC래미안클라시스","district":"남가좌동","area_m2":114.93,"floor":5,"price_10k":91500,"deal_date":"2023-05-20","build_year":2000,"deal_type":"중개거래"},{"name":"동원베네스트","district":"홍은동","area_m2":84.9573,"floor":9,"price_10k":67000,"deal_date":"2023-05-13","build_year":2012,"deal_type":"중개거래"},{"name":"두산","district":"북아현동","area_m2":59.96,"floor":6,"price_10k":77000,"deal_date":"2023-05-20","build_year":1999,"deal_type":"중개거래"},{"name":"e편한세상신촌1단지","district":"북아현동","area_m2":84.93,"floor":17,"price_10k":137700,"deal_date":"2023-05-09","build_year":2018,"deal_type":"중개거래"},{"name":"래미안남가좌2차","district":"남가좌동","area_m2":59.788,"floor":3,"price_10k":80500,"deal_date":"2023-05-26","build_year":2005,"deal_type":"중개거래"},{"name":"DMC래미안클라시스","district":"남가좌동","area_m2":84.9,"floor":6,"price_10k":82900,"deal_date":"2023-05-17","build_year":2000,"deal_type":"중개거래"},{"name":"홍제현대","district":"홍제동","area_m2":119.32,"floor":4,"price_10k":88350,"deal_date":"2023-05-02","build_year":1992,"deal_type":"중개거래"},{"name":"돈의문센트레빌","district":"냉천동","area_m2":59.98,"floor":4,"price_10k":98000,"deal_date":"2023-05-13","build_year":2011,"deal_type":"중개거래"},{"name":"DMC에코자이","district":"남가좌동","area_m2":84.78,"floor":7,"price_10k":109500,"deal_date":"2023-05-17","build_year":2019,"deal_type":"중개거래"},{"name":"홍은미성","district":"홍은동","area_m2":83.61,"floor":8,"price_10k":46000,"deal_date":"2023-05-02","build_year":1985,"deal_type":"직거래"},{"name":"HDX휴팰리스","district":"홍은동","area_m2":59.0362,"floor":12,"price_10k":63000,"deal_date":"2023-05-16","build_year":2018,"deal_type":"중개거래"},{"name":"DMC파크뷰자이1단지","district":"남가좌동","area_m2":121.614,"floor":2,"price_10k":145500,"deal_date":"2023-05-24","build_year":2015,"deal_type":"중개거래"},{"name":"미건스카이빌","district":"홍은동","area_m2":84.92,"floor":8,"price_10k":40000,"deal_date":"2023-05-05","build_year":2003,"deal_type":"중개거래"},{"name":"남가좌동현대","district":"남가좌동","area_m2":59.4,"floor":1,"price_10k":59000,"deal_date":"2023-05-02","build_year":1999,"deal_type":"중개거래"},{"name":"성우아파트","district":"북아현동","area_m2":84.28,"floor":7,"price_10k":105000,"deal_date":"2023-05-20","build_year":2005,"deal_type":"중개거래"},{"name":"남가좌동현대","district":"남가좌동","area_m2":59.4,"floor":7,"price_10k":61000,"deal_date":"2023-05-18","build_year":1999,"deal_type":"중개거래"},{"name":"DMC래미안클라시스","district":"남가좌동","area_m2":59.93,"floor":16,"price_10k":67000,"deal_date":"2023-05-07","build_year":2000,"deal_type":"중개거래"},{"name":"인왕산현대","district":"홍제동","area_m2":59.93,"floor":13,"price_10k":66500,"deal_date":"2023-05-18","build_year":2000,"deal_type":"중개거래"},{"name":"북한산더샵","district":"홍은동","area_m2":84.956,"floor":19,"price_10k":104000,"deal_date":"2023-05-13","build_year":2017,"deal_type":"중개거래"},{"name":"성원","district":"연희동","area_m2":115.06,"floor":13,"price_10k":111000,"deal_date":"2023-05-18","build_year":2001,"deal_type":"중개거래"},{"name":"풍림2","district":"홍은동","area_m2":84.93,"floor":4,"price_10k":65000,"deal_date":"2023-05-20","build_year":1990,"deal_type":"직거래"},{"name":"신촌푸르지오","district":"북아현동","area_m2":84.9738,"floor":7,"price_10k":130000,"deal_date":"2023-05-02","build_year":2015,"deal_type":"중개거래"},{"name":"래미안루센티아","district":"남가좌동","area_m2":84.83,"floor":12,"price_10k":113500,"deal_date":"2023-05-12","build_year":2020,"deal_type":"중개거래"},{"name":"성원","district":"홍제동","area_m2":41.5,"floor":4,"price_10k":42300,"deal_date":"2023-05-18","build_year":1998,"deal_type":"중개거래"},{"name":"e편한세상신촌2단지","district":"북아현동","area_m2":84.93,"floor":12,"price_10k":144000,"deal_date":"2023-05-01","build_year":2018,"deal_type":"중개거래"},{"name":"독립문파크빌","district":"현저동","area_m2":59.4,"floor":3,"price_10k":51500,"deal_date":"2023-05-18","build_year":2000,"deal_type":"중개거래"},{"name":"충정솔레디움(101동)","district":"충정로3가","area_m2":80.47,"floor":3,"price_10k":98000,"deal_date":"2023-05-15","build_year":2005,"deal_type":"중개거래"},{"name":"신촌푸르지오","district":"북아현동","area_m2":59.8802,"floor":2,"price_10k":105000,"deal_date":"2023-05-12","build_year":2015,"deal_type":"중개거래"},{"name":"엘르빌","district":"창천동","area_m2":134.34,"floor":5,"price_10k":90000,"deal_date":"2023-05-09","build_year":2001,"deal_type":"중개거래"},{"name":"서강주상복합","district":"홍은동","area_m2":152.55,"floor":11,"price_10k":57000,"deal_date":"2023-05-17","build_year":1998,"deal_type":"직거래"},{"name":"북한산두산위브","district":"홍은동","area_m2":84.78,"floor":5,"price_10k":81000,"deal_date":"2023-05-13","build_year":2020,"deal_type":"중개거래"},{"name":"DMC센트럴아이파크","district":"남가좌동","area_m2":59.91,"floor":13,"price_10k":86500,"deal_date":"2023-05-07","build_year":2018,"deal_type":"중개거래"},{"name":"혜우","district":"대현동","area_m2":129.27,"floor":15,"price_10k":80000,"deal_date":"2023-05-10","build_year":1996,"deal_type":"중개거래"},{"name":"동부센트레빌","district":"냉천동","area_m2":59.86,"floor":8,"price_10k":68000,"deal_date":"2023-05-13","build_year":2002,"deal_type":"중개거래"},{"name":"행복한","district":"충정로3가","area_m2":43.5,"floor":6,"price_10k":83600,"deal_date":"2023-05-05","build_year":2006,"deal_type":"중개거래"},{"name":"북한산두산위브2차","district":"홍은동","area_m2":59.7501,"floor":12,"price_10k":68200,"deal_date":"2023-05-11","build_year":2021,"deal_type":"중개거래"},{"name":"서강1차(1동)","district":"홍은동","area_m2":71.53,"floor":5,"price_10k":45000,"deal_date":"2023-05-09","build_year":1988,"deal_type":"중개거래"},{"name":"래미안남가좌2차","district":"남가좌동","area_m2":84.806,"floor":9,"price_10k":97000,"deal_date":"2023-05-07","build_year":2005,"deal_type":"중개거래"},{"name":"두산","district":"홍은동","area_m2":59.73,"floor":6,"price_10k":55000,"deal_date":"2023-05-04","build_year":1997,"deal_type":"중개거래"},{"name":"홍제한양","district":"홍제동","area_m2":84.77,"floor":3,"price_10k":74000,"deal_date":"2023-05-03","build_year":1993,"deal_type":"중개거래"},{"name":"서강1차(1동)","district":"홍은동","area_m2":79.7,"floor":3,"price_10k":35000,"deal_date":"2023-05-10","build_year":1988,"deal_type":"직거래"},{"name":"경향빌라트","district":"연희동","area_m2":154.6,"floor":6,"price_10k":127000,"deal_date":"2023-05-03","build_year":1995,"deal_type":"중개거래"},{"name":"남가좌동현대","district":"남가좌동","area_m2":59.4,"floor":2,"price_10k":61500,"deal_date":"2023-05-06","build_year":1999,"deal_type":"중개거래"},{"name":"신촌푸르지오","district":"북아현동","area_m2":84.9572,"floor":8,"price_10k":132200,"deal_date":"2023-05-09","build_year":2015,"deal_type":"중개거래"},{"name":"홍제원현대(459-0)","district":"홍제동","area_m2":59.93,"floor":15,"price_10k":68000,"deal_date":"2023-05-01","build_year":2000,"deal_type":"중개거래"},{"name":"독립문파크빌","district":"현저동","area_m2":59.4,"floor":5,"price_10k":55000,"deal_date":"2023-05-08","build_year":2000,"deal_type":"중개거래"},{"name":"두산","district":"북아현동","area_m2":59.96,"floor":2,"price_10k":58000,"deal_date":"2023-05-06","build_year":1999,"deal_type":"직거래"},{"name":"두산","district":"북아현동","area_m2":59.96,"floor":3,"price_10k":76000,"deal_date":"2023-05-01","build_year":1999,"deal_type":"중개거래"},{"name":"홍은동벽산","district":"홍은동","area_m2":84.78,"floor":4,"price_10k":64000,"deal_date":"2023-05-02","build_year":1997,"deal_type":"중개거래"},{"name":"e편한세상신촌2단지","district":"북아현동","area_m2":84.93,"floor":17,"price_10k":123000,"deal_date":"2023-05-02","build_year":2018,"deal_type":"직거래"},{"name":"성원","district":"홍제동","area_m2":84.87,"floor":12,"price_10k":62000,"deal_date":"2023-05-02","build_year":1998,"deal_type":"중개거래"}],"summary":{"median_price_10k":82900,"min_price_10k":15000,"max_price_10k":191000,"sample_count":119},"total_count":122,"filtered_count":119,"query":{"asset_type":"apartment","deal_type":"trade","lawd_cd":"11410","deal_ymd":"202305"},"proxy":{"name":"k-skill-proxy","cache":{"hit":false,"ttl_ms":300000},"requested_at":"2026-05-06T04:05:28.558Z"}}