{
  "동서울한양": {
    "region": "동대문_답십리",
    "complex_no": "337",
    "date": "2026_05_06",
    "listings": [
      {
        "price": "6억 8,000",
        "area": 59,
        "floor": "3/15",
        "direction": "서향",
        "desc": "O올수리O채광좋은 서향 신혼부부 살기 좋은 예쁜집 ",
        "article_no": "2624568329"
      },
      {
        "price": "6억 4,000",
        "area": 59,
        "floor": "1/15",
        "direction": "동향",
        "desc": "추천 올수리되어 깨끗 입주협의가능 신혼부부추천",
        "article_no": "2623907773"
      },
      {
        "price": "6억 4,000",
        "area": 59,
        "floor": "1/15",
        "direction": "동향",
        "desc": "O추천O전체 올수리 입주협의 가능 신혼부부 추천드려요",
        "article_no": "2623907845"
      },
      {
        "price": "7억",
        "area": 59,
        "floor": "13/15",
        "direction": "동향",
        "desc": "O전체 올수리O전망 최고 좋은 집 입주협의 가능 신혼추천",
        "article_no": "2623892022"
      },
      {
        "price": "6억 8,000",
        "area": 59,
        "floor": "저/15",
        "direction": "서향",
        "desc": "수리되어 깨끗 전세안고 매매",
        "article_no": "2624561638"
      },
      {
        "price": "6억 8,000",
        "area": 59,
        "floor": "저/15",
        "direction": "남서향",
        "desc": "추천 숲세권 밝고 환한집 깔끔한내부 전세안고",
        "article_no": "2624360985"
      },
      {
        "price": "7억",
        "area": 59,
        "floor": "고/15",
        "direction": "동향",
        "desc": "추천,특올수리,전망뷰, 입구동으로 교통편리",
        "article_no": "2624083773"
      },
      {
        "price": "7억 5,000",
        "area": 59,
        "floor": "고/15",
        "direction": "동향",
        "desc": "O특올수리O전망최고 시스템에어컨2 거실확장 신혼부부 추천",
        "article_no": "2623748969"
      },
      {
        "price": "6억",
        "area": 59,
        "floor": "저/15",
        "direction": "동향",
        "desc": "급매 올수리,컨디션굿.전세안고 입주협의",
        "article_no": "2623129962"
      },
      {
        "price": "6억",
        "area": 59,
        "floor": "2/15",
        "direction": "동향",
        "desc": "다주택자매물 무주택자한해서 세안고 매수가능  숲전망 신혼부부추천",
        "article_no": "2621440542"
      },
      {
        "price": "6억 8,000",
        "area": 59,
        "floor": "11/15",
        "direction": "동향",
        "desc": "샷시포함 하여 올수리된 로얄층 입니다",
        "article_no": "2620021243"
      },
      {
        "price": "7억 5,000",
        "area": 59,
        "floor": "3/15",
        "direction": "남동향",
        "desc": "남동향,입구동, 올수리, 입주일 협의",
        "article_no": "2620292181"
      }
    ],
    "error": null
  },
  "동아에코빌": {
    "region": "성북_길음장위",
    "complex_no": "3425",
    "date": "2026_05_06",
    "listings": [
      {
        "price": "8억 4,000",
        "area": 59,
        "floor": "5/23",
        "direction": "동향",
        "desc": "트인뷰 샷시빼고 올수리 거실폴딩도어로확장 집컨디션최상 복도창문설치",
        "article_no": "2623939549"
      },
      {
        "price": "8억 4,000",
        "area": 59,
        "floor": "5/23",
        "direction": "동향",
        "desc": "트인뷰 샷시빼고올수리 거실폴딩도어확장 집상태최상 복도창문설치됨",
        "article_no": "2622917024"
      },
      {
        "price": "8억 2,000",
        "area": 59,
        "floor": "10/23",
        "direction": "남향",
        "desc": "햇볕잘되는 정남향, 대단지 역세권 3룸 아파트, 입구동으로 편리",
        "article_no": "2622928421"
      },
      {
        "price": "8억",
        "area": 59,
        "floor": "저/23",
        "direction": "동향",
        "desc": "기본. 입주협의. 주인거주로 깔끔하게 관리된 집",
        "article_no": "2623689353"
      },
      {
        "price": "8억 4,000",
        "area": 59,
        "floor": "5/23",
        "direction": "동향",
        "desc": "트인뷰 샷시빼고 올수리 거실폴딩도어로확장 집컨디션최상 복도창문설치",
        "article_no": "2621826621"
      },
      {
        "price": "7억 9,000",
        "area": 59,
        "floor": "6/23",
        "direction": "동향",
        "desc": "입주물 도배 장판 싱크대 led 교체되어 깨끗하게관리가된집",
        "article_no": "2621944977"
      },
      {
        "price": "7억 9,000",
        "area": 59,
        "floor": "6/23",
        "direction": "남향",
        "desc": "입주물로 컨디션 좋은집 입구동으로 편리",
        "article_no": "2621945240"
      },
      {
        "price": "8억 1,000",
        "area": 59,
        "floor": "고/22",
        "direction": "동향",
        "desc": "상월곡역 도보5분 역세권 가성비 아파트 강추 매물",
        "article_no": "2622503826"
      },
      {
        "price": "8억 1,000",
        "area": 59,
        "floor": "고/23",
        "direction": "남향",
        "desc": "",
        "article_no": "2622504917"
      }
    ],
    "error": null
  },
  "종암SK": {
    "region": "성북_길음장위",
    "complex_no": "1191",
    "date": "2026_05_06",
    "listings": [
      {
        "price": "8억",
        "area": 59,
        "floor": "1/27",
        "direction": "남동향",
        "desc": "로얄동  저렴한 입주 매물 수리  동북선   교통 좋은 단지",
        "article_no": "2624320093"
      },
      {
        "price": "8억 3,000",
        "area": 59,
        "floor": "25/27",
        "direction": "남동향",
        "desc": "일부수리 27.4월입주 반전세 전망굿  햇살좋고  사대부중 인프라굿",
        "article_no": "2624429907"
      },
      {
        "price": "8억 3,000",
        "area": 59,
        "floor": "25/27",
        "direction": "남동향",
        "desc": "역세권 종전수리 상태좋은 채광전망굿 초중고학군 인프라굿",
        "article_no": "2624510271"
      },
      {
        "price": "8억",
        "area": 59,
        "floor": "1/27",
        "direction": "남동향",
        "desc": "Go 일부 수리 아이있는분 추천 동북선 수혜단지 학군굿 역세권",
        "article_no": "2624549109"
      },
      {
        "price": "8억",
        "area": 59,
        "floor": "1/27",
        "direction": "남동향",
        "desc": "추천 수리한집 상태깨끗 거실확장 정원전망   조용한라인",
        "article_no": "2624509491"
      },
      {
        "price": "8억",
        "area": 59,
        "floor": "1/27",
        "direction": "남동향",
        "desc": "저렴한 입주매물   조용한 로얄동    교통과  학군 좋은  단지",
        "article_no": "2624238916"
      },
      {
        "price": "8억 3,000",
        "area": 59,
        "floor": "25/27",
        "direction": "동향",
        "desc": "로얄동  세안고  저렴   동북선     교통과  학군 좋은  단지",
        "article_no": "2624239251"
      }
    ],
    "error": null
  },
  "월곡두산위브": {
    "region": "성북_길음장위",
    "complex_no": "2990",
    "date": "2026_05_06",
    "listings": [
      {
        "price": "9억 7,000",
        "area": 59,
        "floor": "9/20",
        "direction": "남향",
        "desc": "추천 올확장 선호동 남향 주차장연결동",
        "article_no": "2624468578"
      },
      {
        "price": "9억 7,000",
        "area": 59,
        "floor": "9/20",
        "direction": "남향",
        "desc": "O  남향  풀확장형   접근성굿 전망굿  빠른입주가능",
        "article_no": "2624525561"
      },
      {
        "price": "9억 7,000",
        "area": 59,
        "floor": "9/20",
        "direction": "남향",
        "desc": "입구동으로 주차연결된 남향 최고 로얄동입니다.올확장형 입주가능매물",
        "article_no": "2624505535"
      },
      {
        "price": "9억 7,000",
        "area": 59,
        "floor": "9/20",
        "direction": "남향",
        "desc": "올확장, 남향 주차장연결동, 입구최선호동, 앞뷰있음, 따뜻하고 깔끔한 집",
        "article_no": "2624563477"
      },
      {
        "price": "9억 5,000",
        "area": 59,
        "floor": "12/20",
        "direction": "남향",
        "desc": "입주가능, 탁트인 뷰, 채광우수한 확장형 남향집, 내부상태 굿",
        "article_no": "2624562251"
      },
      {
        "price": "9억 1,000",
        "area": 59,
        "floor": "1/18",
        "direction": "남향",
        "desc": "추천.내부 올수리.남향.확장형.충간소음 걱정 없네요.초품아.숲세권",
        "article_no": "2624352831"
      },
      {
        "price": "9억 5,000",
        "area": 59,
        "floor": "12/20",
        "direction": "남향",
        "desc": "추천.로얄동.남향.부분수리.확장형.초품아.숲세권",
        "article_no": "2624352207"
      },
      {
        "price": "9억 6,000",
        "area": 59,
        "floor": "3/20",
        "direction": "남향",
        "desc": "강력추천, 완전 최근 샷시포함 특올수리, 남향, 트인 조망으로 개방감",
        "article_no": "2624562110"
      },
      {
        "price": "9억 1,000",
        "area": 59,
        "floor": "1/18",
        "direction": "남향",
        "desc": "남향 주차장 연결동.올확장 수리되어 내부 상태 아주 깨끗한 집입니다.",
        "article_no": "2624506837"
      },
      {
        "price": "9억 5,000",
        "area": 59,
        "floor": "12/20",
        "direction": "남향",
        "desc": "급매,확장,전망트여 시원해요,채광 좋은 남향, R동초품아,숲세권",
        "article_no": "2624281548"
      }
    ],
    "error": null
  },
  "길음뉴타운2단지푸르지오": {
    "region": "성북_길음장위",
    "complex_no": "8082",
    "date": "2026_05_06",
    "listings": [
      {
        "price": "10억 6,000",
        "area": 59,
        "floor": "16/18",
        "direction": "남동향",
        "desc": "후문옆 거실방1확장 화2 일조권풍부 밝은조망",
        "article_no": "2624394625"
      },
      {
        "price": "10억 6,000",
        "area": 59,
        "floor": "16/18",
        "direction": "남동향",
        "desc": "o급매에확장된집o인기대단지o하늘뷰에깨끗한밝은집o길음중학교배정o전자계약환영",
        "article_no": "2624399406"
      },
      {
        "price": "10억 3,000",
        "area": 59,
        "floor": "4/18",
        "direction": "남서향",
        "desc": "계단식 화2 밝은집 길원초인접 입주일협의가",
        "article_no": "2624395751"
      },
      {
        "price": "10억 5,000",
        "area": 59,
        "floor": "16/18",
        "direction": "남동향",
        "desc": "0고려대졸0 급매 금액조정가능 계단식 확장형 화2 뻥뷰 길원초 길음중",
        "article_no": "2624424182"
      },
      {
        "price": "10억 3,000",
        "area": 59,
        "floor": "6/17",
        "direction": "남동향",
        "desc": "다주택자 매물, 세안고, 내부깔끔, 전망굿,27년4월입주가능",
        "article_no": "2624490830"
      },
      {
        "price": "10억 3,000",
        "area": 59,
        "floor": "6/17",
        "direction": "남동향",
        "desc": "0추천 계단식 화장실2 전망굿 모든사항협의가 전자계약가 길음중 상태깔끔",
        "article_no": "2624362182"
      },
      {
        "price": "10억 7,000",
        "area": 59,
        "floor": "4/18",
        "direction": "남서향",
        "desc": "탁트인전망 내부컨디션좋음 길원초 입주협의 계단식",
        "article_no": "2624385171"
      },
      {
        "price": "10억 3,000",
        "area": 59,
        "floor": "6/17",
        "direction": "남동향",
        "desc": "계단식 트인뷰 기본 화장실2 도배장판등 부분수리 길음초중교 채광전망좋음",
        "article_no": "2624380764"
      },
      {
        "price": "10억 3,000",
        "area": 59,
        "floor": "6/17",
        "direction": "남동향",
        "desc": "0 계단식 화장실2개 광폭베란다 길원초길음중배정 높은층고환상뷰",
        "article_no": "2623994163"
      }
    ],
    "error": null
  },
  "답십리두산": {
    "region": "동대문_답십리",
    "complex_no": "3271",
    "date": "2026_05_06",
    "listings": [
      {
        "price": "10억 6,000",
        "area": 59,
        "floor": "1/23",
        "direction": "남향",
        "desc": "로얄동,정남향,샷시포함 올수리,확장형,깔끔한 내부",
        "article_no": "2624467171"
      },
      {
        "price": "10억 6,000",
        "area": 59,
        "floor": "1/23",
        "direction": "남향",
        "desc": ".추 천 . 로열동 올수리 확장형 깨끗",
        "article_no": "2624455858"
      },
      {
        "price": "10억 6,000",
        "area": 59,
        "floor": "1/23",
        "direction": "남향",
        "desc": "남향, 3층높이1층, 확장등 전체올수리 깨끗한집,정상입주",
        "article_no": "2624123208"
      },
      {
        "price": "10억 6,000",
        "area": 59,
        "floor": "1/23",
        "direction": "남향",
        "desc": "올수리확장,3층 높이로 층간소음문제 해소,로얄동.",
        "article_no": "2624104899"
      },
      {
        "price": "10억 6,000",
        "area": 59,
        "floor": "1/23",
        "direction": "남향",
        "desc": ". 추 천 . 전체 올수리 정남향 확장형",
        "article_no": "2624042911"
      },
      {
        "price": "10억 8,000",
        "area": 59,
        "floor": "11/23",
        "direction": "동향",
        "desc": "숲전망좋은 막힘없는 뷰.",
        "article_no": "2623865708"
      },
      {
        "price": "10억 6,000",
        "area": 59,
        "floor": "저/23",
        "direction": "남향",
        "desc": "지하철가장가까울로얄동 특급올수리 남향 입주협의",
        "article_no": "2624500325"
      },
      {
        "price": "10억 6,000",
        "area": 59,
        "floor": "저/23",
        "direction": "남향",
        "desc": "역가까운 선호동 남향 올수리. 센스넘치는 인테리어와 좋은일이 가득한 집.",
        "article_no": "2624382683"
      },
      {
        "price": "10억 8,000",
        "area": 59,
        "floor": "저/23",
        "direction": "남향",
        "desc": "선호동 남향 센스있는 올수리. 입주협의.",
        "article_no": "2624035743"
      },
      {
        "price": "10억 8,000",
        "area": 59,
        "floor": "저/23",
        "direction": "남향",
        "desc": "선호동 남향 센스있는 올수리. 입주협의.",
        "article_no": "2623868413"
      },
      {
        "price": "10억 5,000",
        "area": 59,
        "floor": "고/13",
        "direction": "서향",
        "desc": "입구동 부분수리. 입주협의.",
        "article_no": "2623262939"
      },
      {
        "price": "10억 8,000",
        "area": 59,
        "floor": "중/23",
        "direction": "동향",
        "desc": "그린뷰가능하고 앞이 트여 답답함이 없이 잘 사용하고 계십니다.",
        "article_no": "2623149097"
      },
      {
        "price": "10억 8,000",
        "area": 59,
        "floor": "저/23",
        "direction": "남향",
        "desc": "역가까운 선호동 남향.",
        "article_no": "2623149946"
      },
      {
        "price": "10억 8,000",
        "area": 59,
        "floor": "저/23",
        "direction": "남향",
        "desc": "확장올수리된 입주 가능한 주인거주매물입니다",
        "article_no": "2623075144"
      },
      {
        "price": "10억 8,000",
        "area": 59,
        "floor": "중/23",
        "direction": "동향",
        "desc": "앞이 트여있어 개방감있고 깨끗하게 잘 사용하고 계십니다",
        "article_no": "2622284351"
      },
      {
        "price": "10억 8,000",
        "area": 59,
        "floor": "저/23",
        "direction": "남향",
        "desc": "샷시 포함하여 확장 올수리된  편리성 최고인동 남향 입니다",
        "article_no": "2622050397"
      },
      {
        "price": "10억 8,000",
        "area": 59,
        "floor": "중/23",
        "direction": "동향",
        "desc": "앞이 트여있어 개방감있고 깨끗하게 잘 사용하고 계십니다",
        "article_no": "2621594857"
      },
      {
        "price": "10억 6,000",
        "area": 59,
        "floor": "저/23",
        "direction": "남향",
        "desc": "",
        "article_no": "2619501839"
      }
    ],
    "error": null
  },
  "장안래미안2차": {
    "region": "동대문_답십리",
    "complex_no": "8802",
    "date": "2026_05_06",
    "listings": [
      {
        "price": "11억 3,000",
        "area": 64,
        "floor": "17/24",
        "direction": "남향",
        "desc": "25 남향으로 채광좋고 올확장  앞트여서 전망좋은로얄동 협의입주가능",
        "article_no": "2624469172"
      },
      {
        "price": "10억 4,500",
        "area": 54,
        "floor": "고/24",
        "direction": "남향",
        "desc": "남향, 귀한 소형매물, 방3화2, 방1확장, 입주협의",
        "article_no": "2624115826"
      },
      {
        "price": "10억 3,000",
        "area": 54,
        "floor": "중/24",
        "direction": "남향",
        "desc": "남향 귀한소형매물 전세안고 27년2월 입주협의입니다",
        "article_no": "2620516826"
      }
    ],
    "error": null
  },
  "길음뉴타운9단지래미안": {
    "region": "성북_길음장위",
    "complex_no": "26160",
    "date": "2026_05_06",
    "listings": [
      {
        "price": "13억 5,000",
        "area": 59,
        "floor": "2/28",
        "direction": "남향",
        "desc": "YM 추천 남향 시에3 세대창고 내부깨끗 주인거주 입주협의 전자계약가능",
        "article_no": "2624420495"
      },
      {
        "price": "13억 5,000",
        "area": 59,
        "floor": "21/29",
        "direction": "남동향",
        "desc": "SM, 추천 역세권, 확장, 관리잘된집,단지내 마트등 생활편리,세대창고,",
        "article_no": "2624378908"
      },
      {
        "price": "12억 8,000",
        "area": 59,
        "floor": "9/29",
        "direction": "남동향",
        "desc": "YM 추천  올확장  주인거주  내부깨끗  상가이용편리  전자계약가능",
        "article_no": "2623978260"
      },
      {
        "price": "13억 5,000",
        "area": 59,
        "floor": "21/29",
        "direction": "남동향",
        "desc": "YM추천 올확장 내부깨끗 시에3 상가이용편리 8월이후입주협의 전자계약가능",
        "article_no": "2623477989"
      },
      {
        "price": "13억 5,000",
        "area": 59,
        "floor": "21/29",
        "direction": "남동향",
        "desc": "0추천 확장형 내부깔끔 모든사항협의가 세대창고 생활권편리 역세권",
        "article_no": "2624509570"
      }
    ],
    "error": null
  },
  "롯데캐슬클라시아": {
    "region": "성북_길음장위",
    "complex_no": "126062",
    "date": "2026_05_06",
    "listings": [
      {
        "price": "15억 5,000",
        "area": 59,
        "floor": "17/24",
        "direction": "남향",
        "desc": "0선경추천 전망최고 판상형 올확장 에어컨4 조합원풀옵션 길음역가까운동",
        "article_no": "2624472625"
      },
      {
        "price": "15억 5,000",
        "area": 59,
        "floor": "17/20",
        "direction": "남향",
        "desc": "O.정문추천.다주택5.9일이내.입주매물.초역세권.에어컨4.가전풀옵션",
        "article_no": "2624561259"
      },
      {
        "price": "15억 5,000",
        "area": 59,
        "floor": "17/20",
        "direction": "남향",
        "desc": "0착한추천매매 길음역 역세권 판상형 올확장 채광전망굿 입주협의",
        "article_no": "2624498081"
      },
      {
        "price": "15억 5,000",
        "area": 59,
        "floor": "17/24",
        "direction": "남향",
        "desc": "송천추천  올확장 판상형  에어컨4가전풀옵션  시원시원뷰 입주협의",
        "article_no": "2624590213"
      },
      {
        "price": "15억 5,000",
        "area": 59,
        "floor": "2/23",
        "direction": "남향",
        "desc": "0 추천 트인뷰 채광좋음 판상형 올확장 에어컨4대 미아초등학교배정",
        "article_no": "2624505706"
      },
      {
        "price": "15억 5,000",
        "area": 59,
        "floor": "17/20",
        "direction": "남향",
        "desc": "0매매추천 채광좋은남향 냉장고 김냉 에4대 지하철가까운동 입주정상",
        "article_no": "2624587855"
      },
      {
        "price": "15억 5,000",
        "area": 59,
        "floor": "17/24",
        "direction": "남향",
        "desc": "O.정문25.다주택5.9일이내.고층밝은남향.주인거주.에어컨4.가전풀",
        "article_no": "2624559873"
      },
      {
        "price": "15억 5,000",
        "area": 59,
        "floor": "17/20",
        "direction": "남향",
        "desc": "0선경추천 판상형 길음역세권 남향 에어컨4 중문 가전풀옵션",
        "article_no": "2624571835"
      }
    ],
    "error": null
  },
  "래미안길음센터피스": {
    "region": "성북_길음장위",
    "complex_no": "111330",
    "date": "2026_05_06",
    "listings": [
      {
        "price": "15억 2,000",
        "area": 59,
        "floor": "9/20",
        "direction": "남동향",
        "desc": "JEIL 추천. 채광굿 거실넓은 판상형A 올확장 에어컨2 정문입구동",
        "article_no": "2624541238"
      },
      {
        "price": "15억 5,000",
        "area": 59,
        "floor": "8/15",
        "direction": "남동향",
        "desc": "",
        "article_no": "2624578431"
      },
      {
        "price": "15억",
        "area": 59,
        "floor": "9/17",
        "direction": "남동향",
        "desc": "0 행복추천 l 탁트인전망 l 채광훌륭 l 입주협의 l 올확장 l 판상형",
        "article_no": "2624538600"
      },
      {
        "price": "14억 8,000",
        "area": 59,
        "floor": "4/39",
        "direction": "남동향",
        "desc": "0착한추천매매 확장 채광굿 정원뷰 역세권 빠른입주가 ",
        "article_no": "2624482756"
      },
      {
        "price": "14억 5,000",
        "area": 59,
        "floor": "11/12",
        "direction": "남서향",
        "desc": "0. 다주택.27년3월.무주택자가.동북선호재.고층채광밝은집.올확장.에2",
        "article_no": "2624549925"
      },
      {
        "price": "15억 5,000",
        "area": 59,
        "floor": "24/39",
        "direction": "남서향",
        "desc": "0선경추천 로열센터 인기전실넓은C타입 올확장 전망최고 채광우수 입주가",
        "article_no": "2624540895"
      },
      {
        "price": "15억",
        "area": 59,
        "floor": "9/17",
        "direction": "남동향",
        "desc": "0목화 M 최강의 편리함 M 확장 판상 M 트인전망 M 내부최상",
        "article_no": "2624492122"
      },
      {
        "price": "14억 8,000",
        "area": 59,
        "floor": "9/16",
        "direction": "남서향",
        "desc": "JEIL 추천. 올확장 타워형 채광굿 정문입구동 역세권 입주협의",
        "article_no": "2624486571"
      },
      {
        "price": "15억 5,000",
        "area": 59,
        "floor": "24/39",
        "direction": "남서향",
        "desc": "입주협의 올확장 판상형 커뮤니티이용편리 판상형",
        "article_no": "2624492762"
      },
      {
        "price": "14억 5,000",
        "area": 59,
        "floor": "11/12",
        "direction": "남서향",
        "desc": "CEN 무주택자 27년3월입주 백화점 상가 인접동  에어컨2 판상형",
        "article_no": "2624571005"
      },
      {
        "price": "15억",
        "area": 59,
        "floor": "9/17",
        "direction": "북동향",
        "desc": "선경추천 거실뷰 탁트인라인라인 판상A 올확장 동북선수혜 입주협의",
        "article_no": "2624540103"
      },
      {
        "price": "15억",
        "area": 59,
        "floor": "9/16",
        "direction": "남서향",
        "desc": "영훈학교옆 올확장 입구동 입주협의",
        "article_no": "2624480194"
      },
      {
        "price": "14억 8,000",
        "area": 59,
        "floor": "9/16",
        "direction": "남서향",
        "desc": "0우리추천,확장,정문가까운동,주인거주입주협의",
        "article_no": "2624552480"
      },
      {
        "price": "15억 2,000",
        "area": 59,
        "floor": "13/20",
        "direction": "남서향",
        "desc": "영훈학교옆 올확장 에4 입주협의",
        "article_no": "2624481056"
      }
    ],
    "error": null
  },
  "래미안위브": {
    "region": "동대문_답십리",
    "complex_no": "104202",
    "date": "2026_05_06",
    "listings": [
      {
        "price": "15억 4,000",
        "area": 59,
        "floor": "1/10",
        "direction": "동향",
        "desc": "25.올확장.시에2.전동불라인드.무주택자 매수가능.",
        "article_no": "2624590620"
      },
      {
        "price": "15억 4,000",
        "area": 59,
        "floor": "1/10",
        "direction": "동향",
        "desc": "｜TOP｜세안고 또는 입주 올확장 시스템에어컨2 판상형 주인의뢰 공동가능",
        "article_no": "2624572406"
      },
      {
        "price": "15억 8,000",
        "area": 59,
        "floor": "6/13",
        "direction": "남향",
        "desc": "전자계약가능 로얄동 로얄층 올확장 다주택자중과배제물건 생애최조추천",
        "article_no": "2624511364"
      },
      {
        "price": "15억 4,000",
        "area": 59,
        "floor": "1/10",
        "direction": "동향",
        "desc": "25. 올확장. 아이키우기 편한집. 시에2. 전동블라인드. 무주택자 매수",
        "article_no": "2624472528"
      },
      {
        "price": "15억 8,000",
        "area": 59,
        "floor": "6/13",
        "direction": "남향",
        "desc": "전세안고매매 무주택자매수가능 네고가능",
        "article_no": "2624471216"
      },
      {
        "price": "15억 4,000",
        "area": 59,
        "floor": "1/10",
        "direction": "동향",
        "desc": "급매  무주택자5월9일 세안고또는입주가능 올확장 시에2 전동블라인드",
        "article_no": "2624536654"
      },
      {
        "price": "15억 8,000",
        "area": 59,
        "floor": "6/13",
        "direction": "남향",
        "desc": "올확장. 조율가능 늦은잔금OK. 정남향 개방감좋은집 내부깔끔",
        "article_no": "2624448148"
      },
      {
        "price": "15억 4,000",
        "area": 59,
        "floor": "1/10",
        "direction": "동향",
        "desc": "공동가능.급매.5월9일.올확장.무주택자.세안고매매.시스템에어컨.전자계약0",
        "article_no": "2624448840"
      },
      {
        "price": "15억 8,000",
        "area": 59,
        "floor": "6/13",
        "direction": "남향",
        "desc": "채광굿,올확장,세안고,갭10.5억,트인뷰,잘 관리된 집",
        "article_no": "2624480869"
      },
      {
        "price": "15억 8,000",
        "area": 59,
        "floor": "6/13",
        "direction": "남향",
        "desc": "25.올확장.27년1월입주.늦은잔금.전자계약0.공동가능.",
        "article_no": "2624448832"
      },
      {
        "price": "15억 4,000",
        "area": 59,
        "floor": "1/10",
        "direction": "동향",
        "desc": "공동가능. 무주택자 갭매수물건. 올확장 판상형 선호타입 에어컨2",
        "article_no": "2624447613"
      }
    ],
    "error": null
  },
  "래미안크레시티": {
    "region": "동대문_답십리",
    "complex_no": "103797",
    "date": "2026_05_06",
    "listings": [
      {
        "price": "16억 3,000",
        "area": 59,
        "floor": "10/17",
        "direction": "남향",
        "desc": "25.확장형 화장실2 전망굿 깨끗하게 잘 관리된집",
        "article_no": "2624480474"
      }
    ],
    "error": null
  },
  "답십리파크자이": {
    "region": "동대문_답십리",
    "complex_no": "113059",
    "date": "2026_05_06",
    "listings": [
      {
        "price": "15억 4,000",
        "area": 59,
        "floor": "10/20",
        "direction": "동향",
        "desc": "111 시에4.신축아파트,주인거주중,조정가,용마산숲세권,조용주거환경111",
        "article_no": "2624372566"
      },
      {
        "price": "15억 4,000",
        "area": 59,
        "floor": "10/20",
        "direction": "동향",
        "desc": ". 추 천 . 주인 거주 깨끗 시스템에어컨 중문",
        "article_no": "2624455613"
      },
      {
        "price": "15억 4,000",
        "area": 59,
        "floor": "10/20",
        "direction": "동향",
        "desc": "111 시스템에어컨2대.중문,구조좋은신축아파트,주인거주중,조정가 111",
        "article_no": "2624466102"
      },
      {
        "price": "15억 4,000",
        "area": 59,
        "floor": "10/20",
        "direction": "동향",
        "desc": "확장형,시스템에어컨,중문,신축급 내부",
        "article_no": "2624351060"
      },
      {
        "price": "15억 4,000",
        "area": 59,
        "floor": "10/20",
        "direction": "동향",
        "desc": "확장형,시스템에어컨,중문,신축급 내부",
        "article_no": "2624466251"
      },
      {
        "price": "15억 4,000",
        "area": 59,
        "floor": "10/20",
        "direction": "동향",
        "desc": ". 추 천 . 주인 거주 깨끗 시스템에어컨 중문",
        "article_no": "2624354177"
      },
      {
        "price": "15억 4,000",
        "area": 59,
        "floor": "10/20",
        "direction": "동향",
        "desc": "확장, 시에2, 중문등 주인거주 깨끗이 관리된집입니다.",
        "article_no": "2624365717"
      },
      {
        "price": "15억 4,000",
        "area": 59,
        "floor": "10/20",
        "direction": "동향",
        "desc": "지하철역세권 주인거주로관리잘됨 시.에2 입주협의가능 ",
        "article_no": "2624496181"
      },
      {
        "price": "15억 4,000",
        "area": 59,
        "floor": "10/20",
        "direction": "동향",
        "desc": "답십리역 깔끔하게 관리 잘 된 볕 잘드는집 시스템에어컨 중문",
        "article_no": "2624381946"
      }
    ],
    "error": null
  },
  "래미안미드카운티": {
    "region": "동대문_답십리",
    "complex_no": "111223",
    "date": "2026_05_06",
    "listings": [],
    "error": null
  },
  "행당한진타운": {
    "region": "성동_왕십리행당",
    "complex_no": "878",
    "date": "2026_05_06",
    "listings": [
      {
        "price": "16억 5,000",
        "area": 59,
        "floor": "8/25",
        "direction": "남서향",
        "desc": "주인매물,기본,깨끗,개방감좋고 채광좋은집,조용한동 ",
        "article_no": "2624292836"
      },
      {
        "price": "16억",
        "area": 59,
        "floor": "2/25",
        "direction": "동향",
        "desc": "추천. 입주협의. 샷시포함 확장올수리.아래층세대없는2층 아이키우기 좋음",
        "article_no": "2623913770"
      },
      {
        "price": "16억 9,000",
        "area": 59,
        "floor": "14/25",
        "direction": "남서향",
        "desc": "예전올수리,거실베란다샷시교체,로얄동,행현학군,앞트임과 채광좋은집 ",
        "article_no": "2624584391"
      },
      {
        "price": "17억 5,000",
        "area": 59,
        "floor": "15/25",
        "direction": "남서향",
        "desc": "거실확장,특올수리,거실 안방 시스템에어컨,개방감좋은집 ",
        "article_no": "2624574629"
      }
    ],
    "error": null
  },
  "왕십리자이": {
    "region": "성동_왕십리행당",
    "complex_no": "111002",
    "date": "2026_05_06",
    "listings": [
      {
        "price": "20억",
        "area": 59,
        "floor": "14/20",
        "direction": "남동향",
        "desc": "다주택 매물 조용한동  남동 남서 양방향  추천급매물 ",
        "article_no": "2624184414"
      },
      {
        "price": "17억",
        "area": 59,
        "floor": "저/20",
        "direction": "남동향",
        "desc": "입주가능, 조용한 양방향 조망 뷰",
        "article_no": "2624485914"
      },
      {
        "price": "19억",
        "area": 59,
        "floor": "고/20",
        "direction": "남동향",
        "desc": "확장형, 에어컨2, 남서향 밝은집",
        "article_no": "2624184733"
      },
      {
        "price": "18억",
        "area": 59,
        "floor": "중/20",
        "direction": "남향",
        "desc": "올확장 판상형 남향 로얄동 대중교통이용편리 ",
        "article_no": "2623942024"
      }
    ],
    "error": null
  },
  "사당롯데캐슬골든포레": {
    "region": "동작_사당이수",
    "complex_no": "115936",
    "date": "2026_05_06",
    "listings": [
      {
        "price": "16억",
        "area": 59,
        "floor": "16/18",
        "direction": "남동향",
        "desc": "로얄동.층, 판상형으로 최선호 타입, 시내 및 서달산 뷰 최고 전망",
        "article_no": "2624487440"
      },
      {
        "price": "16억",
        "area": 59,
        "floor": "16/18",
        "direction": "남향",
        "desc": "최 선호동, 드레스 룸2, 다 주택자 매물, 탁트인 조망, 숲세권,학교접",
        "article_no": "2624530134"
      },
      {
        "price": "16억",
        "area": 59,
        "floor": "16/18",
        "direction": "남동향",
        "desc": "급매, 28P안방넓고 드레스룸 2개, 탁트인 조망, 입주나 임차인 안고",
        "article_no": "2624527431"
      },
      {
        "price": "16억",
        "area": 59,
        "floor": "16/18",
        "direction": "남향",
        "desc": "선호 타입, 드레스룸 2개, 탁 트인 조망,상태 최상, 로얄 동,숲세권",
        "article_no": "2624428279"
      },
      {
        "price": "16억",
        "area": 59,
        "floor": "16/18",
        "direction": "남동향",
        "desc": "깔끔, 실제28P, 입주나 임차인안고,드레스룸2개, 탁트인조망,채광굳",
        "article_no": "2624444266"
      },
      {
        "price": "16억",
        "area": 59,
        "floor": "16/18",
        "direction": "남동향",
        "desc": "전세승계다주택자추천매물  귀한타입  신혼부부강추",
        "article_no": "2624459479"
      },
      {
        "price": "16억",
        "area": 59,
        "floor": "16/18",
        "direction": "남동향",
        "desc": "급매 신혼부부 강력추천 입주및 전세승계 공동ok",
        "article_no": "2624357005"
      },
      {
        "price": "16억",
        "area": 59,
        "floor": "저/18",
        "direction": "남향",
        "desc": "막힘없는 전망 입주가 확장형 시스템에어컨등",
        "article_no": "2624564468"
      }
    ],
    "error": null
  }
}